ru_soundex/__init__.py
ru_soundex/distance.py
ru_soundex/soundex.py
ru_soundex-1.1.1.dist-info/DESCRIPTION.rst
ru_soundex-1.1.1.dist-info/METADATA
ru_soundex-1.1.1.dist-info/RECORD
ru_soundex-1.1.1.dist-info/WHEEL
ru_soundex-1.1.1.dist-info/metadata.json
ru_soundex-1.1.1.dist-info/top_level.txt
