Metadata-Version: 2.0
Name: ru-soundex
Version: 1.1.1
Summary: Soundex algorithm for russian, english and finnish languages
Home-page: https://github.com/roddar92/russian_soundex
Author: Daria Rodionova
Author-email: drodionova86@gmail.com
License: MIT
Platform: UNKNOWN
Classifier: Intended Audience :: Developers
Classifier: Intended Audience :: Science/Research
Classifier: Natural Language :: Russian
Classifier: Natural Language :: Finnish
Classifier: Programming Language :: Python :: 3.5
Classifier: Topic :: Text Processing :: Linguistic
Requires-Dist: editdistance
Requires-Dist: pymorphy2
